LICENSE
MANIFEST.in
README.rst
setup.py
chembl_core_db/__init__.py
chembl_core_db/chemicalValidators.py
chembl_core_db/models.py
chembl_core_db/tests.py
chembl_core_db/utils.py
chembl_core_db.egg-info/PKG-INFO
chembl_core_db.egg-info/SOURCES.txt
chembl_core_db.egg-info/dependency_links.txt
chembl_core_db.egg-info/not-zip-safe
chembl_core_db.egg-info/requires.txt
chembl_core_db.egg-info/top_level.txt
chembl_core_db/cache/__init__.py
chembl_core_db/cache/backends/MongoDBCache.py
chembl_core_db/cache/backends/__init__.py
chembl_core_db/db/__init__.py
chembl_core_db/db/customFields.py
chembl_core_db/db/customManagers.py
chembl_core_db/db/backends/__init__.py
chembl_core_db/db/backends/oracleChEmbl/__init__.py
chembl_core_db/db/backends/oracleChEmbl/base.py
chembl_core_db/db/backends/oracleChEmbl/features.py
chembl_core_db/db/backends/oracleChEmbl/introspection.py
chembl_core_db/db/backends/oracleChEmbl/operations.py
chembl_core_db/db/backends/oracleChEmbl/utils.py
chembl_core_db/db/models/__init__.py
chembl_core_db/db/models/abstractModel.py
chembl_core_db/db/models/lookups.py
chembl_core_db/testing/__init__.py
chembl_core_db/testing/tastypieTest.py